lunacept/__init__.py
lunacept/__main__.py
lunacept/config.py
lunacept/exception_hook.py
lunacept/instrumentor.py
lunacept/output.py
lunacept/parse.py
lunacept-0.4.7.dist-info/METADATA
lunacept-0.4.7.dist-info/WHEEL
lunacept-0.4.7.dist-info/top_level.txt
lunacept-0.4.7.dist-info/RECORD
