Metadata-Version: 2.4
Name: lunacept
Version: 0.4.7
Summary: Enhanced exception analysis library for Python - prints detailed information about what happened when an exception occurs
Author-email: LorewalkerZhou <zhoubobuct@gmail.com>
License: MIT
Project-URL: Homepage, https://github.com/LorewalkerZhou/lunacept
Classifier: Development Status :: 3 - Alpha
Classifier: License :: OSI Approved :: MIT License
Classifier: Programming Language :: Python :: 3
Classifier: Programming Language :: Python :: 3.11
Classifier: Programming Language :: Python :: 3.12
Classifier: Operating System :: OS Independent
Classifier: Topic :: Software Development :: Debuggers
Requires-Python: >=3.11
Requires-Dist: rich>=13.0.0
